arches_lingo/__init__.py
arches_lingo/apps.py
arches_lingo/celery.py
arches_lingo/const.py
arches_lingo/hosts.py
arches_lingo/query_expressions.py
arches_lingo/querysets.py
arches_lingo/serializers.py
arches_lingo/settings.py
arches_lingo/settings_local.py
arches_lingo/tasks.py
arches_lingo/urls.py
arches_lingo/wsgi.py
arches_lingo/datatypes/__init__.py
arches_lingo/etl_modules/__init__.py
arches_lingo/etl_modules/migrate_to_lingo.py
arches_lingo/functions/__init__.py
arches_lingo/locale/.gitkeep
arches_lingo/locale/messages.pot
arches_lingo/management/__init__.py
arches_lingo/management/commands/__init__.py
arches_lingo/media/css/themes/_project.scss
arches_lingo/media/img/favicon.png
arches_lingo/media/js/views/root.js
arches_lingo/media/js/views/components/etl_modules/migrate-to-lingo.js
arches_lingo/migrations/0001_initial.py
arches_lingo/migrations/0002_load_lingo_lists.py
arches_lingo/migrations/__init__.py
arches_lingo/pkg/package_config.json
arches_lingo/pkg/business_data/files/.gitkeep
arches_lingo/pkg/business_data/relations/.gitkeep
arches_lingo/pkg/business_data/resource_views/.gitkeep
arches_lingo/pkg/extensions/bindings/.gitkeep
arches_lingo/pkg/extensions/card_components/.gitkeep
arches_lingo/pkg/extensions/css/.gitkeep
arches_lingo/pkg/extensions/datatypes/.gitkeep
arches_lingo/pkg/extensions/etl_modules/.gitkeep
arches_lingo/pkg/extensions/functions/.gitkeep
arches_lingo/pkg/extensions/plugins/.gitkeep
arches_lingo/pkg/extensions/widgets/.gitkeep
arches_lingo/pkg/graphs/branches/.gitkeep
arches_lingo/pkg/graphs/resource_models/.gitkeep
arches_lingo/pkg/graphs/resource_models/Concept.json
arches_lingo/pkg/graphs/resource_models/Person.json
arches_lingo/pkg/graphs/resource_models/Place.json
arches_lingo/pkg/graphs/resource_models/Scheme.json
arches_lingo/pkg/graphs/resource_models/digital_object_rdm_system.json
arches_lingo/pkg/graphs/resource_models/group_rdm_system.json
arches_lingo/pkg/graphs/resource_models/period_rdm_system.json
arches_lingo-1.0.0b0.dist-info/licenses/LICENSE
arches_lingo-1.0.0b0.dist-info/METADATA
arches_lingo-1.0.0b0.dist-info/WHEEL
arches_lingo-1.0.0b0.dist-info/top_level.txt
arches_lingo-1.0.0b0.dist-info/RECORD
