Metadata-Version: 2.4
Name: arches-lingo
Version: 1.0.0b0
Summary: An Arches application designed to support the creation of thesaurus/vocabulary data.
Author: Arches Project
License-Expression: AGPL-3.0-or-later
Project-URL: Homepage, https://archesproject.org/
Project-URL: Documentation, https://arches.readthedocs.io
Project-URL: Repository, https://github.com/archesproject/arches-lingo.git
Project-URL: Issues, https://github.com/archesproject/arches-lingo/issues
Classifier: Development Status :: 3 - Alpha
Classifier: Programming Language :: Python
Classifier: Programming Language :: Python :: 3
Classifier: Programming Language :: Python :: 3 :: Only
Classifier: Programming Language :: Python :: 3.11
Classifier: Programming Language :: Python :: 3.12
Classifier: Programming Language :: Python :: 3.13
Classifier: Framework :: Django
Classifier: Framework :: Django :: 5.2
Classifier: Intended Audience :: Developers
Classifier: Intended Audience :: Information Technology
Requires-Python: >=3.11
License-File: LICENSE
Requires-Dist: arches==8.1.0a3
Requires-Dist: arches_component_lab==0.0.1a3
Requires-Dist: arches_querysets==1.0.0
Requires-Dist: arches_controlled_lists==1.0.0
Dynamic: license-file
